reversedns/__init__.py
reversedns/client.py
reversedns/version.py
reversedns/exceptions/__init__.py
reversedns/exceptions/error.py
reversedns/models/__init__.py
reversedns/models/base.py
reversedns/models/request.py
reversedns/models/response.py
reversedns/net/__init__.py
reversedns/net/http.py
reverse_dns-1.0.0.dist-info/AUTHORS.rst
reverse_dns-1.0.0.dist-info/LICENSE
reverse_dns-1.0.0.dist-info/METADATA
reverse_dns-1.0.0.dist-info/WHEEL
reverse_dns-1.0.0.dist-info/top_level.txt
reverse_dns-1.0.0.dist-info/RECORD
